dhis2api/.DS_Store
dhis2api/__init__.py
dhis2api/country.py
dhis2api/generate_params.py
dhis2api/indicator_loader.py
dhis2api/param_formatter.py
dhis2api-0.2.2.dist-info/METADATA
dhis2api-0.2.2.dist-info/WHEEL
dhis2api-0.2.2.dist-info/RECORD
